<?xml version="1.0" encoding="UTF-8"?>
<struct name="IslandHudStruct" type="multi">
    <properties>
        <struct ID="0x305B3232" template="Structs/UnknownStruct29.xml"/>
        <property ID="0xA4F20C17" type="file" extensions="STRG"/>
        <property ID="0xE9336455" type="file" extensions="STRG"/>
        <property ID="0x770BCD3B" type="file" extensions="STRG"/>
        <property ID="0xDBFFFA66" type="file" extensions="STRG"/>
        <property ID="0x0EECD488" type="file" extensions="STRG"/>
        <property ID="0x37FD1913" type="file" extensions="STRG"/>
        <property ID="0xA14F34CA" type="file" extensions="STRG"/>
        <property ID="0x3DC0F2BE" type="file" extensions="STRG"/>
        <property ID="0x6FDABAD6" type="file" extensions="STRG"/>
        <property ID="0xE119319B" type="file" extensions="TXTR"/>
    </properties>
</struct>
