<?xml version="1.0" encoding="UTF-8"?>
<PropertyTemplate ArchiveVer="4" Game="DKCReturns">
    <PropertyArchetype Type="Struct">
        <Name>JungleBossStructD</Name>
        <SubProperties>
            <Element Type="Struct" ID="0x12D98DC2" Archetype="VolcanoBossBodyPartStructA"/>
            <Element Type="Struct" ID="0xC0F12817" Archetype="VolcanoBossBodyPartStructA"/>
            <Element Type="Struct" ID="0xF8019F49" Archetype="VolcanoBossBodyPartStructA"/>
            <Element Type="Float" ID="0x4AF1E57A">
                <DefaultValue>50.0</DefaultValue>
            </Element>
        </SubProperties>
    </PropertyArchetype>
</PropertyTemplate>
