<?xml version="1.0" encoding="UTF-8"?>
<PropertyTemplate ArchiveVer="4" Game="PrimeRemaster">
    <PropertyArchetype Type="Struct">
        <Name>Color</Name>
        <SubProperties>
            <Element Type="Float" ID="0x110889d1">
                <Name>R</Name>
                <DefaultValue>0.0</DefaultValue>
            </Element>
            <Element Type="Float" ID="0x8a7aff22">
                <Name>G</Name>
                <DefaultValue>0.0</DefaultValue>
            </Element>
            <Element Type="Float" ID="0x2a5349e9">
                <Name>B</Name>
                <DefaultValue>0.0</DefaultValue>
            </Element>
            <Element Type="Float" ID="0xe364c93a">
                <Name>A</Name>
                <DefaultValue>0.0</DefaultValue>
            </Element>
        </SubProperties>
    </PropertyArchetype>
</PropertyTemplate>
