<?xml version="1.0" encoding="UTF-8"?>
<PropertyTemplate ArchiveVer="4" Game="Echoes">
    <PropertyArchetype Type="Struct">
        <Name>UnknownStruct30</Name>
        <SubProperties>
            <Element Type="Asset" ID="0x55744160">
                <TypeFilter>
                    <Element>AFSM</Element>
                    <Element>FSM2</Element>
                </TypeFilter>
            </Element>
            <Element Type="Struct" ID="0xCF90D15E" Archetype="HealthInfo">
                <SubProperties>
                    <Element Type="Float" ID="0x3A2D17E4">
                        <DefaultValue>2.0</DefaultValue>
                    </Element>
                </SubProperties>
            </Element>
            <Element Type="Float" ID="0xC6C16427">
                <DefaultValue>20.0</DefaultValue>
            </Element>
            <Element Type="Asset" ID="0x2367F689">
                <TypeFilter>
                    <Element>PART</Element>
                </TypeFilter>
            </Element>
            <Element Type="Asset" ID="0xE8A6E174">
                <TypeFilter>
                    <Element>PART</Element>
                </TypeFilter>
            </Element>
            <Element Type="Asset" ID="0x1AB2B090">
                <TypeFilter>
                    <Element>PART</Element>
                </TypeFilter>
            </Element>
            <Element Type="Asset" ID="0x1CCFA4BA">
                <TypeFilter>
                    <Element>PART</Element>
                </TypeFilter>
            </Element>
            <Element Type="Sound" ID="0x4CAB30A9">
                <DefaultValue>0</DefaultValue>
            </Element>
            <Element Type="Sound" ID="0x8F83BE73">
                <DefaultValue>0</DefaultValue>
            </Element>
            <Element Type="Sound" ID="0xB392943A">
                <DefaultValue>0</DefaultValue>
            </Element>
            <Element Type="Sound" ID="0x24ECC1E9">
                <DefaultValue>0</DefaultValue>
            </Element>
            <Element Type="Sound" ID="0x4489935E">
                <DefaultValue>0</DefaultValue>
            </Element>
            <Element Type="Struct" ID="0x7B71AE90" Archetype="DamageVulnerability"/>
        </SubProperties>
    </PropertyArchetype>
</PropertyTemplate>
