<?xml version="1.0" encoding="UTF-8"?>
<PropertyTemplate ArchiveVer="4" Game="CorruptionProto">
    <PropertyArchetype Type="Struct">
        <Name>VisorParameters</Name>
        <SubProperties>
            <Element Type="Bool" ID="0xFE9DC266">
                <DefaultValue>false</DefaultValue>
            </Element>
            <Element Type="Int" ID="0xCA19E8C6">
                <DefaultValue>15</DefaultValue>
            </Element>
        </SubProperties>
    </PropertyArchetype>
</PropertyTemplate>
